fractal_database_matrix/__init__.py
fractal_database_matrix/admin.py
fractal_database_matrix/apps.py
fractal_database_matrix/broker.py
fractal_database_matrix/migrations/0001_initial.py
fractal_database_matrix/migrations/__init__.py
fractal_database_matrix/models.py
fractal_database_matrix/representations.py
fractal_database_matrix-0.0.6.dist-info/LICENSE
fractal_database_matrix-0.0.6.dist-info/METADATA
fractal_database_matrix-0.0.6.dist-info/WHEEL
fractal_database_matrix-0.0.6.dist-info/RECORD
