Metadata-Version: 2.1
Name: fractal-database-matrix
Version: 0.0.6
Summary: 
Author: Justin
Author-email: jrussel1055@gmail.com
Requires-Python: >=3.10,<4.0
Classifier: Programming Language :: Python :: 3
Classifier: Programming Language :: Python :: 3.10
Classifier: Programming Language :: Python :: 3.11
Classifier: Programming Language :: Python :: 3.12
Provides-Extra: dev
Requires-Dist: django (>=5.0.0,<6.0.0)
Requires-Dist: fractal-cli (>=0.0.1)
Requires-Dist: fractal-matrix-client (>=0.0.1)
Requires-Dist: ipython (>=8.17.2,<9.0.0) ; extra == "dev"
Requires-Dist: matrix-nio (>=0.22.1,<0.23.0)
Requires-Dist: pytest (>=7.4.3,<8.0.0) ; extra == "dev"
Requires-Dist: pytest-asyncio (>=0.21.1,<0.22.0) ; extra == "dev"
Requires-Dist: pytest-cov (>=4.1.0,<5.0.0) ; extra == "dev"
Requires-Dist: pytest-django (>=4.5.2,<5.0.0) ; extra == "dev"
Requires-Dist: pytest-mock (>=3.11.1,<4.0.0) ; extra == "dev"
Requires-Dist: taskiq-matrix (>=0.0.1)
